<?xml version="1.0" encoding="UTF-8"?>
    <root>
        <rootURL>http://behappyplz.deviantart.com/</rootURL>
        <toBrowse>
            <url>http://behappyplz.deviantart.com/stats/gallery/</url>
            <url>http://behappyplz.deviantart.com/art/Be-Happy-Plz-64403840</url>
            <url>http://behappyplz.deviantart.com/journal/be-happy-everyone-plz-239601617</url>
            <url>http://behappyplz.deviantart.com/journal/?offset=1</url>
            <url>http://behappyplz.deviantart.com/?offset=10</url>
            <url>http://behappyplz.deviantart.com/?offset=20</url>
            <url>http://behappyplz.deviantart.com/?offset=offset</url>
            <url>http://behappyplz.deviantart.com</url>
            <url>http://behappyplz.deviantart.com/gallery/</url>
            <url>http://behappyplz.deviantart.com/gallery/?catpath=/</url>
            <url>http://behappyplz.deviantart.com/gallery/?catpath=scraps</url>
            <url>http://behappyplz.deviantart.com/gallery/?q=on</url>
            <url>http://behappyplz.deviantart.com/prints/</url>
            <url>http://behappyplz.deviantart.com/prints/?utm_campaign=printstab&amp;utm_medium=userpage&amp;utm_source=deviantart</url>
            <url>http://behappyplz.deviantart.com/favourites/</url>
            <url>http://behappyplz.deviantart.com/favourites/?catpath=/</url>
            <url>http://behappyplz.deviantart.com/journal/</url>
            <url>http://behappyplz.deviantart.com/journal/?catpath=/</url>
        </toBrowse>
        <browsed>
            <url_data uri="http://behappyplz.deviantart.com/">
                <header name="status" value="200"/>
                <header name="content-length" value="109408"/>
                <header name="content-location" value="http://behappyplz.deviantart.com/"/>
                <header name="transfer-encoding" value="chunked"/>
                <header name="set-cookie" value="userinfo=__429d399e539aaca97081%3B%7B%22username%22%3A%22%22%2C%22uniqueid%22%3A%22190d19e81bb8ddf18a4559877d22289c%22%2C%22hitcount%22%3A2%2C%22visitcount%22%3A2%2C%22visittime%22%3A1344193911%2C%22firstvisit%22%3A1344193911%7D; expires=Tue, 04-Sep-2012 19:11:51 GMT; path=/; domain=.deviantart.com"/>
                <header name="vary" value="Accept-Encoding"/>
                <header name="server" value="Apache"/>
                <header name="link_encoding" value="iso-8859-1"/>
                <header name="cache-control" value="private"/>
                <header name="date" value="Sun, 05 Aug 2012 19:11:51 GMT"/>
                <header name="p3p" value="policyref=&quot;/w3c/p3p.xml&quot;, CP=&quot;NOI DSP COR CURa OUR STP&quot;"/>
                <header name="content-type" value="text/html"/>
            </url_data>
            <url_data uri="http://behappyplz.deviantart.com/journal/">
                <header name="status" value="200"/>
                <header name="content-length" value="49135"/>
                <header name="content-location" value="http://behappyplz.deviantart.com/journal/"/>
                <header name="transfer-encoding" value="chunked"/>
                <header name="set-cookie" value="userinfo=__21a748d88cefa4d7961c%3B%7B%22username%22%3A%22%22%2C%22uniqueid%22%3A%228f39bc5ac6f88e772929371bc66beaed%22%2C%22hitcount%22%3A2%2C%22visitcount%22%3A2%2C%22visittime%22%3A1344193914%2C%22firstvisit%22%3A1344193914%7D; expires=Tue, 04-Sep-2012 19:11:54 GMT; path=/; domain=.deviantart.com"/>
                <header name="vary" value="Accept-Encoding"/>
                <header name="server" value="Apache"/>
                <header name="link_encoding" value="iso-8859-1"/>
                <header name="cache-control" value="private"/>
                <header name="date" value="Sun, 05 Aug 2012 19:11:54 GMT"/>
                <header name="p3p" value="policyref=&quot;/w3c/p3p.xml&quot;, CP=&quot;NOI DSP COR CURa OUR STP&quot;"/>
                <header name="content-type" value="text/html"/>
            </url_data>
            <url_data uri="http://behappyplz.deviantart.com/gallery/">
                <header name="status" value="200"/>
                <header name="content-length" value="50521"/>
                <header name="content-location" value="http://behappyplz.deviantart.com/gallery/"/>
                <header name="transfer-encoding" value="chunked"/>
                <header name="set-cookie" value="userinfo=__25db8453f0079a74bcd0%3B%7B%22username%22%3A%22%22%2C%22uniqueid%22%3A%22a247cae7d82823e9f7e051450c1dc263%22%2C%22hitcount%22%3A2%2C%22visitcount%22%3A2%2C%22visittime%22%3A1344193913%2C%22firstvisit%22%3A1344193912%7D; expires=Tue, 04-Sep-2012 19:11:53 GMT; path=/; domain=.deviantart.com"/>
                <header name="vary" value="Accept-Encoding"/>
                <header name="server" value="Apache"/>
                <header name="link_encoding" value="iso-8859-1"/>
                <header name="cache-control" value="private"/>
                <header name="date" value="Sun, 05 Aug 2012 19:11:52 GMT"/>
                <header name="p3p" value="policyref=&quot;/w3c/p3p.xml&quot;, CP=&quot;NOI DSP COR CURa OUR STP&quot;"/>
                <header name="content-type" value="text/html"/>
            </url_data>
            <url_data uri="http://behappyplz.deviantart.com/prints/?utm_campaign=printstab&amp;utm_medium=userpage&amp;utm_source=deviantart">
                <header name="status" value="200"/>
                <header name="content-length" value="36296"/>
                <header name="content-location" value="http://behappyplz.deviantart.com/prints/?utm_campaign=printstab&amp;utm_medium=userpage&amp;utm_source=deviantart"/>
                <header name="transfer-encoding" value="chunked"/>
                <header name="set-cookie" value="userinfo=__de55f02c67fd50dc3989%3B%7B%22username%22%3A%22%22%2C%22uniqueid%22%3A%22810e7ebb4fcfe635b490c5a5f446386b%22%2C%22hitcount%22%3A2%2C%22visitcount%22%3A2%2C%22visittime%22%3A1344193913%2C%22firstvisit%22%3A1344193913%7D; expires=Tue, 04-Sep-2012 19:11:53 GMT; path=/; domain=.deviantart.com"/>
                <header name="vary" value="Accept-Encoding"/>
                <header name="server" value="Apache"/>
                <header name="link_encoding" value="iso-8859-1"/>
                <header name="cache-control" value="private"/>
                <header name="date" value="Sun, 05 Aug 2012 19:11:53 GMT"/>
                <header name="p3p" value="policyref=&quot;/w3c/p3p.xml&quot;, CP=&quot;NOI DSP COR CURa OUR STP&quot;"/>
                <header name="content-type" value="text/html"/>
            </url_data>
            <url_data uri="http://behappyplz.deviantart.com">
                <header name="status" value="200"/>
                <header name="content-length" value="109401"/>
                <header name="content-location" value="http://behappyplz.deviantart.com"/>
                <header name="transfer-encoding" value="chunked"/>
                <header name="set-cookie" value="userinfo=__346132e6cce97c8d35f2%3B%7B%22username%22%3A%22%22%2C%22uniqueid%22%3A%22008ff4d5776ace2da65b1728f2a4bd83%22%2C%22hitcount%22%3A2%2C%22visitcount%22%3A2%2C%22visittime%22%3A1344193912%2C%22firstvisit%22%3A1344193911%7D; expires=Tue, 04-Sep-2012 19:11:52 GMT; path=/; domain=.deviantart.com"/>
                <header name="vary" value="Accept-Encoding"/>
                <header name="server" value="Apache"/>
                <header name="link_encoding" value="iso-8859-1"/>
                <header name="cache-control" value="private"/>
                <header name="date" value="Sun, 05 Aug 2012 19:11:51 GMT"/>
                <header name="p3p" value="policyref=&quot;/w3c/p3p.xml&quot;, CP=&quot;NOI DSP COR CURa OUR STP&quot;"/>
                <header name="content-type" value="text/html"/>
            </url_data>
            <url_data uri="http://behappyplz.deviantart.com/favourites/">
                <header name="status" value="200"/>
                <header name="content-length" value="48516"/>
                <header name="content-location" value="http://behappyplz.deviantart.com/favourites/"/>
                <header name="transfer-encoding" value="chunked"/>
                <header name="set-cookie" value="userinfo=__ef525c7c75acc883d6a3%3B%7B%22username%22%3A%22%22%2C%22uniqueid%22%3A%2266d3d31c8e0f8455e097cffdc317ba6f%22%2C%22hitcount%22%3A2%2C%22visitcount%22%3A2%2C%22visittime%22%3A1344193913%2C%22firstvisit%22%3A1344193913%7D; expires=Tue, 04-Sep-2012 19:11:53 GMT; path=/; domain=.deviantart.com"/>
                <header name="vary" value="Accept-Encoding"/>
                <header name="server" value="Apache"/>
                <header name="link_encoding" value="iso-8859-1"/>
                <header name="cache-control" value="private"/>
                <header name="date" value="Sun, 05 Aug 2012 19:11:53 GMT"/>
                <header name="p3p" value="policyref=&quot;/w3c/p3p.xml&quot;, CP=&quot;NOI DSP COR CURa OUR STP&quot;"/>
                <header name="content-type" value="text/html"/>
            </url_data>
        </browsed>
        <forms/>
        <uploads/>
    </root>
