<?xml version="1.0" encoding="UTF-8"?>
    <root>
        <rootURL>http://beinggeekchic.com/</rootURL>
        <toBrowse>
            <url>http://beinggeekchic.com/post/1044292252/things-to-do-at-the-wizarding-world-of-harry-potter</url>
            <url>http://beinggeekchic.com/tagged/books</url>
            <url>http://beinggeekchic.com/tagged/freebies</url>
            <url>http://beinggeekchic.com/tagged/Geeky_at_Work</url>
            <url>http://beinggeekchic.com/tagged/Geeky_at_Home</url>
            <url>http://beinggeekchic.com/tagged/DIY</url>
            <url>http://beinggeekchic.com/tagged/video</url>
            <url>http://beinggeekchic.com/post/28698152817/diy-weekend-a-geode-rock-ring-for-earthy-ladies</url>
            <url>http://beinggeekchic.com/post/28491434485/geeky-at-work-blinded-by-science</url>
            <url>http://beinggeekchic.com/tagged/DIY-Weekend</url>
            <url>http://beinggeekchic.com/tagged/fashion</url>
            <url>http://beinggeekchic.com/tagged/jewelry</url>
            <url>http://beinggeekchic.com/tagged/science</url>
            <url>http://beinggeekchic.com/post/28630066018/this-week-in-geek-harry-potter-fan-finds-magic-gene</url>
            <url>http://beinggeekchic.com/tagged/This-week-in-geek</url>
            <url>http://beinggeekchic.com/tagged/Harry-Potter</url>
            <url>http://beinggeekchic.com/tagged/Thor</url>
            <url>http://beinggeekchic.com/tagged/Doctor-Who</url>
            <url>http://beinggeekchic.com/post/28562493814/guest-post-internet-ruining-your-attention-span</url>
            <url>http://beinggeekchic.com/tagged/Sarah-Von</url>
            <url>http://beinggeekchic.com/tagged/advice</url>
            <url>http://beinggeekchic.com/tagged/guest-post</url>
            <url>http://beinggeekchic.com/tagged/internet</url>
            <url>http://beinggeekchic.com/tagged/life</url>
            <url>http://beinggeekchic.com/tagged/Geeky-at-Work</url>
            <url>http://beinggeekchic.com/tagged/music</url>
            <url>http://beinggeekchic.com/post/28425350970/turn-your-instagrams-into-photostrips-with-boothgram</url>
            <url>http://beinggeekchic.com/tagged/instagram</url>
            <url>http://beinggeekchic.com/tagged/photography</url>
            <url>http://beinggeekchic.com/tagged/tech</url>
            <url>http://beinggeekchic.com/post/28411694679/lady-geek-of-the-week-janet-varney</url>
            <url>http://beinggeekchic.com/tagged/LGOTW</url>
            <url>http://beinggeekchic.com/tagged/podcasts</url>
            <url>http://beinggeekchic.com/tagged/Watchmen</url>
            <url>http://beinggeekchic.com/tagged/Nerdist</url>
            <url>http://beinggeekchic.com/page/2</url>
            <url>http://beinggeekchic.com/about</url>
            <url>http://beinggeekchic.com/post/12080822003/the-anatomy-of-my-katniss-everdeen-halloween</url>
            <url>http://beinggeekchic.com/post/20346882967/a-commentary-on-fake-geeks-acceptance</url>
            <url>http://beinggeekchic.com/post/22813431733/the-only-thing-joss-whedon-got-wrong-in-the-avengers</url>
            <url>http://beinggeekchic.com/post/18138563082/top-10-reasons-why-jk-rowlings-new-book-made-my-year</url>
            <url>http://beinggeekchic.com/post/18971603175/on-ambition-being-what-you-do</url>
            <url>http://beinggeekchic.com/tagged/harry-potter</url>
            <url>http://beinggeekchic.com/tagged/LEGO</url>
            <url>http://beinggeekchic.com/tagged/star-wars</url>
            <url>http://beinggeekchic.com/tagged/hunger-games</url>
            <url>http://beinggeekchic.com/tagged/game-of-thrones</url>
            <url>http://beinggeekchic.com/tagged/sherlock</url>
            <url>http://beinggeekchic.com/tagged/sci-fi</url>
            <url>http://beinggeekchic.com/tagged/comics</url>
            <url>http://beinggeekchic.com/tagged/crafty</url>
            <url>http://beinggeekchic.com/tagged/apple</url>
            <url>http://beinggeekchic.com/tagged/design</url>
            <url>http://beinggeekchic.com/tagged/video-games</url>
            <url>http://beinggeekchic.com/sponsors</url>
            <url>http://beinggeekchic.com/search</url>
            <url>http://beinggeekchic.com/search?q=on</url>
            <url>http://beinggeekchic.com/archive/2012/1</url>
            <url>http://beinggeekchic.com/archive/2012/2</url>
            <url>http://beinggeekchic.com/archive/2012/3</url>
            <url>http://beinggeekchic.com/archive/2012/4</url>
            <url>http://beinggeekchic.com/archive/2012/5</url>
            <url>http://beinggeekchic.com/archive/2012/6</url>
            <url>http://beinggeekchic.com/archive/2012/7</url>
            <url>http://beinggeekchic.com/archive/2012/8</url>
            <url>http://beinggeekchic.com/archive/2011/1</url>
            <url>http://beinggeekchic.com/archive/2011/2</url>
            <url>http://beinggeekchic.com/archive/2011/3</url>
            <url>http://beinggeekchic.com/archive/2011/4</url>
            <url>http://beinggeekchic.com/archive/2011/5</url>
            <url>http://beinggeekchic.com/archive/2011/6</url>
            <url>http://beinggeekchic.com/archive/2011/7</url>
            <url>http://beinggeekchic.com/archive/2011/8</url>
            <url>http://beinggeekchic.com/archive/2011/9</url>
            <url>http://beinggeekchic.com/archive/2011/10</url>
            <url>http://beinggeekchic.com/archive/2011/11</url>
            <url>http://beinggeekchic.com/archive/2011/12</url>
            <url>http://beinggeekchic.com/archive/2010/4</url>
            <url>http://beinggeekchic.com/archive/2010/5</url>
            <url>http://beinggeekchic.com/archive/2010/6</url>
            <url>http://beinggeekchic.com/archive/2010/7</url>
            <url>http://beinggeekchic.com/archive/2010/8</url>
            <url>http://beinggeekchic.com/archive/2010/9</url>
            <url>http://beinggeekchic.com/archive/2010/10</url>
            <url>http://beinggeekchic.com/archive/2010/11</url>
            <url>http://beinggeekchic.com/archive/2010/12</url>
            <url>http://beinggeekchic.com/post/28347197176/geeky-at-home-sometimes-this-nerd-needs-a-drink</url>
            <url>http://beinggeekchic.com/post/28296381120/in-which-i-sarcastically-ask-do-we-need-geek-ids</url>
            <url>http://beinggeekchic.com/post/28135233490/this-week-in-geek-lego-museum-space-documentary-and</url>
            <url>http://beinggeekchic.com/post/28097072720/how-to-plan-a-geek-tastic-vacation</url>
            <url>http://beinggeekchic.com/post/27981497495/geeky-at-work-inside-my-laptop-bag</url>
            <url>http://beinggeekchic.com/post/27922099200/lady-geek-of-the-week-shelley-summitt</url>
            <url>http://beinggeekchic.com/post/27849250990/geeky-at-home-my-multi-purpose-craft-space</url>
            <url>http://beinggeekchic.com/post/27793804626/diy-weekend-comic-book-bracelets</url>
            <url>http://beinggeekchic.com/post/27640952949/this-week-in-geek-game-of-thrones-baby-names-smart</url>
            <url>http://beinggeekchic.com/post/27560158587/phone-and-tablet-wallpaper-freebies-for-banner-stark</url>
            <url>http://beinggeekchic.com/post/27496246140/major-fashion-houses-gleaning-inspiration-from-geek</url>
            <url>http://beinggeekchic.com/post/27413011915/lady-geek-of-the-week-carolynn-duncan</url>
            <url>http://beinggeekchic.com/post/27380695923/geeky-at-home-wannabe-brit-tips-on-painting</url>
            <url>http://beinggeekchic.com/post/27350046222/giveaway-winner-misc-announcements</url>
            <url>http://beinggeekchic.com/post/27123466377/this-week-in-geek-vacation-is-for-eating-and-stars-are</url>
            <url>http://beinggeekchic.com/post/27081184056/guest-post-books-worthy-of-a-re-read</url>
            <url>http://beinggeekchic.com/post/26984296342/geeky-on-vacation-summer-sun</url>
            <url>http://beinggeekchic.com/post/26941319923/lady-geek-of-the-week-beca-lewis-skeels</url>
            <url>http://beinggeekchic.com/post/26841699476/summer-reads-giveaway-mothership-john-hughes-dvds</url>
            <url>http://beinggeekchic.com/post/26829602655/geeky-at-home-i-love-chrome</url>
            <url>http://beinggeekchic.com/post/26722983244/fab-freebies-doctor-who-iphone-android-background</url>
            <url>http://beinggeekchic.com/post/26636675056/this-week-in-geek-givenchy-loves-game-of-thrones</url>
            <url>http://beinggeekchic.com/post/26605707963/youre-a-geek-and-its-your-birthday</url>
            <url>http://beinggeekchic.com/post/26528255740/yay-a-national-holiday</url>
            <url>http://beinggeekchic.com/post/26417390914/lady-geek-of-the-week-jamie-frevele</url>
            <url>http://beinggeekchic.com/post/26365617542/geeky-at-home-vintage-popular-science-covers</url>
            <url>http://beinggeekchic.com/post/26254464618/diy-weekend-easy-1-instagram-art-video</url>
            <url>http://beinggeekchic.com/post/26150201817/this-week-in-geek-rip-nora-marvels-next-movie</url>
            <url>http://beinggeekchic.com/post/26069289917/spider-man-and-the-decay-rate-algorithm-or-nerdy-mathy</url>
            <url>http://beinggeekchic.com/post/26007010251/geeky-at-work-the-stylish-geek-in-star-wars</url>
            <url>http://beinggeekchic.com/post/25936959365/lady-geek-of-the-week-sophie-of-sweetcheeks-stitches</url>
            <url>http://beinggeekchic.com/post/25860447400/geeky-at-home-my-ultimate-office-accessories-list</url>
            <url>http://beinggeekchic.com/post/25833280425/just-call-me-she-hulk</url>
            <url>http://beinggeekchic.com/post/25666254537/this-week-in-geek-june-16th-22nd</url>
            <url>http://beinggeekchic.com/post/25580746762/guest-post-a-smart-girl-is-a-sexy-girl</url>
            <url>http://beinggeekchic.com/post/25534637160/geeky-at-work-neon-arrows-on-the-run</url>
            <url>http://beinggeekchic.com/post/25457095131/lady-geek-of-the-week-samantha-of-geeky-sweetheart</url>
            <url>http://beinggeekchic.com/post/25370708124/geeky-at-home-nerds-go-shopping</url>
            <url>http://beinggeekchic.com/post/25337926231/adventures-in-competitive-parade-float-making-with-my</url>
            <url>http://beinggeekchic.com/post/25200482895/diy-weekend-constellation-ipad-case-video</url>
            <url>http://beinggeekchic.com/post/25156545493/this-week-in-geek-june-9th-15th</url>
            <url>http://beinggeekchic.com/post/25141205953/cant-wait-to-tackle-my-summer-2012-reading-list</url>
            <url>http://beinggeekchic.com/post/25066811225/geeky-at-work-mollie-aka-my-bookworm-bestie</url>
            <url>http://beinggeekchic.com/post/24984993059/lady-geek-of-the-week-emma-sherlock</url>
            <url>http://beinggeekchic.com/archive?before_time=1339544160</url>
            <url>http://beinggeekchic.com/tagged/katniss-everdeen</url>
            <url>http://beinggeekchic.com/post/21816189556/geeky-at-work-an-arrow-for-katniss-everdeen</url>
            <url>http://beinggeekchic.com/post/9776939154/diy-weekend-upgrade-your-blazer</url>
            <url>http://beinggeekchic.com/tagged/Katniss-Everdeen</url>
            <url>http://beinggeekchic.com/post/19730215903/last-minute-hunger-games-diy-projects-video</url>
            <url>http://beinggeekchic.com/post/12145528986/katniss-everdeen-costume-diy-mockingjay-pin</url>
            <url>http://beinggeekchic.com/post/12145560400/katniss-everdeen-costume-diy-arrows</url>
            <url>http://beinggeekchic.com/post/12145567068/katniss-everdeen-costume-diy-quiver</url>
            <url>http://beinggeekchic.com/post/12146388598/here-i-am-before-heading-out-for-a-halloween-night</url>
            <url>http://beinggeekchic.com/post/19554176395/diy-weekend-mockingjay-pendant-necklace</url>
            <url>http://beinggeekchic.com/post/15088354183/diy-weekend-katnisss-arrow-earrings</url>
            <url>http://beinggeekchic.com/post/19215432922/geeky-at-home-host-a-hunger-games-dinner-party</url>
            <url>http://beinggeekchic.com/post/19608791910/geeky-at-home-a-cocktail-for-cinna</url>
            <url>http://beinggeekchic.com/tagged/Hunger-Games</url>
            <url>http://beinggeekchic.com/tagged/Mockingjay</url>
            <url>http://beinggeekchic.com/post/19294983256/lets-make-the-3-finger-salute-happen-on-twitter</url>
            <url>http://beinggeekchic.com/tagged/The-Hunger-Games</url>
            <url>http://beinggeekchic.com/tagged/Twitter</url>
            <url>http://beinggeekchic.com/tagged/social-media</url>
            <url>http://beinggeekchic.com/post/18469994067/lady-geek-of-the-week-emily-ansara-baines</url>
            <url>http://beinggeekchic.com/tagged/Feist</url>
            <url>http://beinggeekchic.com/tagged/Jenny-Lewis</url>
            <url>http://beinggeekchic.com/post/19123070137/diy-weekend-katniss-everdeen-costume</url>
            <url>http://beinggeekchic.com/tagged/katniss+everdeen/page/2</url>
        </toBrowse>
        <browsed>
            <url_data uri="http://beinggeekchic.com/tagged/katniss-everdeen">
                <header name="status" value="200"/>
                <header name="content-length" value="64505"/>
                <header name="x-robots-tag" value="noindex"/>
                <header name="x-whom" value="proxy03.dfw01"/>
                <header name="vary" value="Accept-Encoding"/>
                <header name="x-tumblr-user" value="beinggeekchic"/>
                <header name="server" value="nginx"/>
                <header name="connection" value="keep-alive"/>
                <header name="link" value="&lt;http://25.media.tumblr.com/avatar_6272a24499e1_16.png&gt;; rel=icon"/>
                <header name="link_encoding" value="utf-8"/>
                <header name="date" value="Sun, 05 Aug 2012 19:16:42 GMT"/>
                <header name="p3p" value="CP=&quot;ALL ADM DEV PSAi COM OUR OTRo STP IND ONL&quot;"/>
                <header name="content-type" value="text/html; charset=UTF-8"/>
                <header name="x-tumblr-usec" value="D=182099"/>
                <header name="content-location" value="http://beinggeekchic.com/tagged/katniss-everdeen"/>
            </url_data>
            <url_data uri="http://beinggeekchic.com/rss">
                <header name="status" value="200"/>
                <header name="content-length" value="10721"/>
                <header name="x-robots-tag" value="noindex"/>
                <header name="x-whom" value="proxy03.dfw01"/>
                <header name="x-tumblr-user" value="beinggeekchic"/>
                <header name="expires" value="Fri, 01 Jan 1990 00:00:00 GMT"/>
                <header name="vary" value="Accept-Encoding"/>
                <header name="server" value="nginx"/>
                <header name="connection" value="keep-alive"/>
                <header name="link_encoding" value="utf-8"/>
                <header name="pragma" value="no-cache"/>
                <header name="cache-control" value="no-cache, must-revalidate"/>
                <header name="date" value="Sun, 05 Aug 2012 19:16:41 GMT"/>
                <header name="p3p" value="CP=&quot;ALL ADM DEV PSAi COM OUR OTRo STP IND ONL&quot;"/>
                <header name="content-type" value="text/xml; charset=utf-8"/>
                <header name="x-tumblr-usec" value="D=187154"/>
                <header name="content-location" value="http://beinggeekchic.com/rss"/>
            </url_data>
            <url_data uri="http://beinggeekchic.com/about">
                <header name="status" value="200"/>
                <header name="content-length" value="41954"/>
                <header name="content-location" value="http://beinggeekchic.com/about"/>
                <header name="x-whom" value="proxy03.dfw01"/>
                <header name="vary" value="Accept-Encoding"/>
                <header name="x-tumblr-user" value="beinggeekchic"/>
                <header name="server" value="nginx"/>
                <header name="connection" value="keep-alive"/>
                <header name="link" value="&lt;http://25.media.tumblr.com/avatar_6272a24499e1_16.png&gt;; rel=icon"/>
                <header name="link_encoding" value="utf-8"/>
                <header name="date" value="Sun, 05 Aug 2012 19:16:41 GMT"/>
                <header name="p3p" value="CP=&quot;ALL ADM DEV PSAi COM OUR OTRo STP IND ONL&quot;"/>
                <header name="content-type" value="text/html; charset=UTF-8"/>
                <header name="x-tumblr-usec" value="D=86655"/>
            </url_data>
            <url_data uri="http://beinggeekchic.com/">
                <header name="status" value="200"/>
                <header name="content-length" value="73108"/>
                <header name="content-location" value="http://beinggeekchic.com/"/>
                <header name="x-whom" value="proxy03.dfw01"/>
                <header name="vary" value="Accept-Encoding"/>
                <header name="x-tumblr-user" value="beinggeekchic"/>
                <header name="server" value="nginx"/>
                <header name="connection" value="keep-alive"/>
                <header name="link" value="&lt;http://25.media.tumblr.com/avatar_6272a24499e1_16.png&gt;; rel=icon"/>
                <header name="link_encoding" value="utf-8"/>
                <header name="date" value="Sun, 05 Aug 2012 19:16:41 GMT"/>
                <header name="p3p" value="CP=&quot;ALL ADM DEV PSAi COM OUR OTRo STP IND ONL&quot;"/>
                <header name="content-type" value="text/html; charset=UTF-8"/>
                <header name="x-tumblr-usec" value="D=215640"/>
            </url_data>
            <url_data uri="http://beinggeekchic.com/sponsors">
                <header name="status" value="200"/>
                <header name="content-length" value="37080"/>
                <header name="content-location" value="http://beinggeekchic.com/sponsors"/>
                <header name="x-whom" value="proxy03.dfw01"/>
                <header name="vary" value="Accept-Encoding"/>
                <header name="x-tumblr-user" value="beinggeekchic"/>
                <header name="server" value="nginx"/>
                <header name="connection" value="keep-alive"/>
                <header name="link" value="&lt;http://25.media.tumblr.com/avatar_6272a24499e1_16.png&gt;; rel=icon"/>
                <header name="link_encoding" value="utf-8"/>
                <header name="date" value="Sun, 05 Aug 2012 19:16:41 GMT"/>
                <header name="p3p" value="CP=&quot;ALL ADM DEV PSAi COM OUR OTRo STP IND ONL&quot;"/>
                <header name="content-type" value="text/html; charset=UTF-8"/>
                <header name="x-tumblr-usec" value="D=77007"/>
            </url_data>
            <url_data uri="http://beinggeekchic.com/archive">
                <header name="status" value="200"/>
                <header name="content-length" value="122310"/>
                <header name="x-robots-tag" value="noindex"/>
                <header name="x-whom" value="proxy03.dfw01"/>
                <header name="vary" value="Accept-Encoding"/>
                <header name="x-tumblr-user" value="beinggeekchic"/>
                <header name="server" value="nginx"/>
                <header name="connection" value="keep-alive"/>
                <header name="link_encoding" value="utf-8"/>
                <header name="date" value="Sun, 05 Aug 2012 19:16:42 GMT"/>
                <header name="p3p" value="CP=&quot;ALL ADM DEV PSAi COM OUR OTRo STP IND ONL&quot;"/>
                <header name="content-type" value="text/html; charset=UTF-8"/>
                <header name="x-tumblr-usec" value="D=688651"/>
                <header name="content-location" value="http://beinggeekchic.com/archive"/>
            </url_data>
        </browsed>
        <forms/>
        <uploads/>
    </root>
